arginfer/__init__.py
arginfer/__main__.py
arginfer/_version.py
arginfer/argbook.py
arginfer/cli.py
arginfer/initialARG.py
arginfer/mcmc.py
arginfer/plots.py
arginfer/provenance.py
arginfer/treeSequence.py
arginfer-0.1.dev78.dist-info/LICENSE
arginfer-0.1.dev78.dist-info/METADATA
arginfer-0.1.dev78.dist-info/WHEEL
arginfer-0.1.dev78.dist-info/entry_points.txt
arginfer-0.1.dev78.dist-info/top_level.txt
arginfer-0.1.dev78.dist-info/RECORD
