Metadata-Version: 2.1
Name: arginfer
Version: 0.1.dev78
Summary: Infer the Ancestral Recombination Graph
Home-page: http://pypi.python.org/pypi/arginfer
Author: Ali Mahmoudi
Author-email: alimahmoodi29@gmail.com
License: UNKNOWN
Project-URL: Source, https://github.com/alimahmoudi29/arginfer
Project-URL: Bug Reports, https://github.com/alimahmoudi29/arginfer/issues
Platform: UNKNOWN
Classifier: Programming Language :: Python :: 3
Classifier: Programming Language :: Python :: 3.6
Classifier: License :: OSI Approved :: MIT License
Classifier: Operating System :: MacOS :: MacOS X
Classifier: Operating System :: POSIX
Classifier: Development Status :: 3 - Alpha
Requires-Python: >=3.4
Requires-Dist: msprime
Requires-Dist: numpy
Requires-Dist: pandas
Requires-Dist: bintrees
Requires-Dist: tqdm
Requires-Dist: sortedcontainers
